autoresearcher/__init__.py
autoresearcher/data_sources/__init__.py
autoresearcher/data_sources/web_apis/__init__.py
autoresearcher/data_sources/web_apis/base_web_api_data_loader.py
autoresearcher/data_sources/web_apis/semantic_scholar_loader.py
autoresearcher/data_sources/web_apis/wikipedia_loader.py
autoresearcher/llms/__init__.py
autoresearcher/llms/openai.py
autoresearcher/utils/__init__.py
autoresearcher/utils/count_tokens.py
autoresearcher/utils/generate_keyword_combinations.py
autoresearcher/utils/get_citations.py
autoresearcher/utils/prompts.py
autoresearcher/workflows/__init__.py
autoresearcher/workflows/literature_review/__init__.py
autoresearcher/workflows/literature_review/combine_answers.py
autoresearcher/workflows/literature_review/extract_answers_from_papers.py
autoresearcher/workflows/literature_review/extract_citations.py
autoresearcher/workflows/literature_review/literature_review.py
autoresearcher-0.0.8.dist-info/LICENSE
autoresearcher-0.0.8.dist-info/METADATA
autoresearcher-0.0.8.dist-info/WHEEL
autoresearcher-0.0.8.dist-info/top_level.txt
autoresearcher-0.0.8.dist-info/RECORD
